tensor_task/__init__.py
tensor_task/tensor_task.py
tensor_teak-0.1.0.dist-info/METADATA
tensor_teak-0.1.0.dist-info/WHEEL
tensor_teak-0.1.0.dist-info/top_level.txt
tensor_teak-0.1.0.dist-info/RECORD
