Metadata-Version: 2.1
Name: tensor-teak
Version: 0.1.0
Summary: A simple Python module with a test function
Home-page: https://github.com
Author: jancey
Author-email: jancey.email@example.com
Classifier: Programming Language :: Python :: 3
Classifier: License :: OSI Approved :: MIT License
Classifier: Operating System :: OS Independent
